[
  {
    "nama": "Software Engineer",
    "syarat": "Syarat baru",
    "deskripsi": "create software using the Kotlin language and create APIs",
    "Status": 0,
    "periode": "01/05/2023",
    "IDLowongan": 1
  },
  {
    "nama": "Graphic Designer",
    "syarat": "Experience in Adobe Premier Pro",
    "deskripsi": "Create a new product design that will launcing",
    "Status": 0,
    "periode": "05/07/2024",
    "IDLowongan": 2
  },
  {
    "nama": "Marketing Manager",
    "syarat": "MBA in Marketing",
    "deskripsi": "Make a marketing plan",
    "Status": 0,
    "periode": "28/05/2024",
    "IDLowongan": 3
  },
  {
    "nama": "Software Developer",
    "syarat": "Master in Computer Science",
    "deskripsi": "make software with flutter",
    "Status": 0,
    "periode": "01/05/2024",
    "IDLowongan": 4
  }
]